{
    "problem_id": 1350,
    "source": "Geometry3k-1398",
    "problem_level": 1,
    "problem_img": "1350.png",
    "construction_cdl": [
        "Shape(OC,CA,AO)",
        "Shape(OA,AB,BO)",
        "Collinear(CAB)"
    ],
    "text_cdl": [
        "Equal(LengthOfLine(AB),5)",
        "Equal(LengthOfLine(AC),15)",
        "Equal(LengthOfLine(OB),21.5)",
        "Equal(LengthOfLine(OC),8)",
        "IsAltitudeOfTriangle(OC,OAB)",
        "PerpendicularBetweenLine(OC,AC)"
    ],
    "image_cdl": [
        "Equal(LengthOfLine(AB),5)",
        "Equal(LengthOfLine(AC),15)",
        "Equal(LengthOfLine(OB),21.5)",
        "Equal(LengthOfLine(OC),8)",
        "IsAltitudeOfTriangle(OC,OAB)",
        "PerpendicularBetweenLine(OC,AC)"
    ],
    "goal_cdl": "Value(AreaOfTriangle(OAB))",
    "problem_answer": "20",
    "theorem_seqs": [
        "triangle_area_formula_common(1,OAB)"
    ],
    "theorem_seqs_dag": {
        "START": [
            "triangle_area_formula_common(1,OAB)"
        ]
    }
}