{
    "problem_id": 1701,
    "source": "Geometry3k-1765",
    "problem_level": 1,
    "problem_img": "1701.png",
    "construction_cdl": [
        "Shape(HW,WX,XH)",
        "Shape(HW,WP,PH)",
        "Shape(XW,WQ,QX)",
        "Shape(PX,XQ,QA,AP)",
        "Collinear(HXQ)",
        "Collinear(HPA)",
        "Collinear(WXP)",
        "Collinear(WQA)"
    ],
    "text_cdl": [
        "Equal(LengthOfLine(AP),3*y+11)",
        "Equal(LengthOfLine(PH),7*y-5)",
        "Equal(MeasureOfAngle(HWQ),4*x-16)",
        "Equal(MeasureOfAngle(HWX),x+12)",
        "Equal(MeasureOfAngle(QAP),3*x-2)",
        "IsBisectorOfAngle(WP,HWA)",
        "IsMedianOfTriangle(WP,WAH)"
    ],
    "image_cdl": [],
    "goal_cdl": "Value(x)",
    "problem_answer": "20",
    "theorem_seqs": [
        "angle_addition(1,HWX,XWQ)"
    ],
    "theorem_seqs_dag": {
        "START": [
            "angle_addition(1,HWX,XWQ)"
        ]
    }
}