{
    "problem_id": 1828,
    "source": "Geometry3k-1896",
    "problem_level": 1,
    "problem_img": "1828.png",
    "construction_cdl": [
        "Shape(EDC,ECA,AD)",
        "Shape(EDC,DB,BC)",
        "Shape(EAD,DA)",
        "Collinear(BDA)",
        "Cocircular(E,DCA)"
    ],
    "text_cdl": [
        "Equal(MeasureOfAngle(DBC),2*x)",
        "Equal(MeasureOfArc(ECA),9*x-1)",
        "Equal(MeasureOfArc(EDC),94)",
        "IsTangentOfCircle(BC,E)"
    ],
    "image_cdl": [
        "Equal(MeasureOfAngle(DBC),2*x)",
        "Equal(MeasureOfArc(ECA),9*x-1)",
        "Equal(MeasureOfArc(EDC),94)",
        "IsTangentOfCircle(BC,E)"
    ],
    "goal_cdl": "Value(x)",
    "problem_answer": "19",
    "theorem_seqs": [
        "circle_property_circular_power_tangent_and_segment_angle(2,BC,BDA,E)"
    ],
    "theorem_seqs_dag": {
        "START": [
            "circle_property_circular_power_tangent_and_segment_angle(2,BC,BDA,E)"
        ]
    }
}