{
    "problem_id": 2127,
    "source": "Geometry3k-2219",
    "problem_level": 2,
    "problem_img": "2127.png",
    "construction_cdl": [
        "Shape(FB,BE,EF)",
        "Shape(BF,FC)",
        "Shape(CF,FG,GC)",
        "Shape(GF,FE)",
        "Shape(CG,GA)",
        "Shape(AG,GD,DA)",
        "Shape(HA,AD)",
        "Collinear(CFB)",
        "Collinear(CGD)",
        "Collinear(BFGAH)"
    ],
    "text_cdl": [
        "Equal(MeasureOfAngle(BEF),78)",
        "Equal(MeasureOfAngle(DGF),120)",
        "Equal(MeasureOfAngle(FBE),50)",
        "Equal(MeasureOfAngle(GDA),56)"
    ],
    "image_cdl": [
        "Equal(MeasureOfAngle(BEF),78)",
        "Equal(MeasureOfAngle(DGF),120)",
        "Equal(MeasureOfAngle(FBE),50)",
        "Equal(MeasureOfAngle(GDA),56)"
    ],
    "goal_cdl": "Value(MeasureOfAngle(GFE))",
    "problem_answer": "128",
    "theorem_seqs": [
        "triangle_property_angle_sum(1,FBE)",
        "adjacent_complementary_angle(1,GFE,EFB)"
    ],
    "theorem_seqs_dag": {
        "START": [
            "triangle_property_angle_sum(1,FBE)",
            "adjacent_complementary_angle(1,GFE,EFB)"
        ]
    }
}