{
    "problem_id": 2200,
    "source": "Geometry3k-2297",
    "problem_level": 3,
    "problem_img": "2200.png",
    "construction_cdl": [
        "Shape(BD,DE,EB)",
        "Shape(EA,AC,CE)",
        "Collinear(BEA)",
        "Collinear(DEC)"
    ],
    "text_cdl": [
        "Equal(MeasureOfAngle(ABD),75)",
        "Equal(MeasureOfAngle(ACD),28)",
        "Equal(MeasureOfAngle(BDC),35)"
    ],
    "image_cdl": [
        "Equal(MeasureOfAngle(ABD),75)",
        "Equal(MeasureOfAngle(ACD),28)",
        "Equal(MeasureOfAngle(BDC),35)"
    ],
    "goal_cdl": "Value(MeasureOfAngle(BAC))",
    "problem_answer": "82",
    "theorem_seqs": [
        "triangle_property_angle_sum(1,BDE)",
        "vertical_angle(1,DEB,CEA)",
        "triangle_property_angle_sum(1,EAC)"
    ],
    "theorem_seqs_dag": {
        "START": [
            "triangle_property_angle_sum(1,BDE)",
            "vertical_angle(1,DEB,CEA)",
            "triangle_property_angle_sum(1,EAC)"
        ]
    }
}