{
    "problem_id": 2346,
    "source": "Geometry3k-2460",
    "problem_level": 1,
    "problem_img": "2346.png",
    "construction_cdl": [
        "Shape(AC,CB,BA)"
    ],
    "text_cdl": [
        "Equal(LengthOfLine(AB),61)",
        "Equal(LengthOfLine(AC),29)",
        "Equal(LengthOfLine(BC),50)",
        "Equal(MeasureOfAngle(ACB),x)"
    ],
    "image_cdl": [
        "Equal(LengthOfLine(AB),61)",
        "Equal(LengthOfLine(AC),29)",
        "Equal(LengthOfLine(BC),50)",
        "Equal(MeasureOfAngle(ACB),x)"
    ],
    "goal_cdl": "Value(x)",
    "problem_answer": "180*acos(-19/145)/pi",
    "theorem_seqs": [
        "cosine_theorem(1,CBA)"
    ],
    "theorem_seqs_dag": {
        "START": [
            "cosine_theorem(1,CBA)"
        ]
    }
}