{
    "problem_id": 2659,
    "source": "Geometry3k-2796",
    "problem_level": 1,
    "problem_img": "2659.png",
    "construction_cdl": [
        "Shape(XW,WY,BXY)",
        "Shape(ZX,BXZ)",
        "Shape(XZ,BZX)",
        "Collinear(CZXW)",
        "Collinear(AYW)",
        "Cocircular(B,YZX)"
    ],
    "text_cdl": [
        "Equal(MeasureOfAngle(XWY),49)",
        "Equal(MeasureOfArc(BXY),96)",
        "IsCentreOfCircle(B,B)"
    ],
    "image_cdl": [
        "Equal(MeasureOfAngle(XWY),49)",
        "Equal(MeasureOfArc(BXY),96)",
        "IsCentreOfCircle(B,B)"
    ],
    "goal_cdl": "Value(MeasureOfArc(BYZ))",
    "problem_answer": "194",
    "theorem_seqs": [
        "circle_property_circular_power_tangent_and_segment_angle(2,WY,WXZ,B)"
    ],
    "theorem_seqs_dag": {
        "START": [
            "circle_property_circular_power_tangent_and_segment_angle(2,WY,WXZ,B)"
        ]
    }
}