{
    "problem_id": 3634,
    "source": "GeoQA-1317",
    "problem_level": 4,
    "problem_img": "3634.png",
    "construction_cdl": [
        "Shape(CB,BA)",
        "Shape(BC,CE,EF,FB)",
        "Shape(EC,CD,DF,FE)",
        "Collinear(BFD)"
    ],
    "text_cdl": [
        "Equal(MeasureOfAngle(CBA),46)",
        "Equal(MeasureOfAngle(FEC),160)",
        "ParallelBetweenLine(AB,EF)",
        "ParallelBetweenLine(EF,CD)"
    ],
    "image_cdl": [],
    "goal_cdl": "Value(MeasureOfAngle(BCE))",
    "problem_answer": "26",
    "theorem_seqs": [
        "parallel_judgment_par_par(1,AB,EF,CD)",
        "parallel_property_alternate_interior_angle(2,AB,CD)",
        "parallel_property_ipsilateral_internal_angle(1,EF,CD)",
        "angle_addition(1,BCE,ECD)"
    ],
    "theorem_seqs_dag": {
        "START": [
            "parallel_judgment_par_par(1,AB,EF,CD)",
            "parallel_property_ipsilateral_internal_angle(1,EF,CD)",
            "angle_addition(1,BCE,ECD)"
        ],
        "parallel_judgment_par_par(1,AB,EF,CD)": [
            "parallel_property_alternate_interior_angle(2,AB,CD)"
        ]
    }
}