{
    "problem_id": 4082,
    "source": "GeoQA-2437",
    "problem_level": 2,
    "problem_img": "4082.png",
    "construction_cdl": [
        "Shape(AB,BC,CA)",
        "Shape(CE,ED,DC)",
        "Collinear(ACE)",
        "Collinear(BCD)"
    ],
    "text_cdl": [
        "Equal(LengthOfLine(AB),1/2)",
        "Equal(LengthOfLine(BC),1)",
        "Equal(LengthOfLine(CD),12)",
        "SimilarBetweenTriangle(CAB,CED)"
    ],
    "image_cdl": [],
    "goal_cdl": "Value(LengthOfLine(DE))",
    "problem_answer": "6",
    "theorem_seqs": [
        "similar_triangle_property_line_ratio(1,CAB,CED)",
        "similar_triangle_property_line_ratio(1,ABC,EDC)"
    ],
    "theorem_seqs_dag": {
        "START": [
            "similar_triangle_property_line_ratio(1,CAB,CED)",
            "similar_triangle_property_line_ratio(1,ABC,EDC)"
        ]
    }
}