{
    "problem_id": 4777,
    "source": "GeoQA-4161",
    "problem_level": 6,
    "problem_img": "4777.png",
    "construction_cdl": [
        "Shape(PC,CE,ED,DP)",
        "Shape(BD,DE,OBE)",
        "Shape(EC,CA,OEA)",
        "Collinear(BDP)",
        "Collinear(ACP)",
        "Collinear(CED)",
        "Cocircular(O,BEA)"
    ],
    "text_cdl": [
        "Equal(LengthOfLine(PA),15)",
        "IsCentreOfCircle(O,O)",
        "IsTangentOfCircle(CA,O)",
        "IsTangentOfCircle(CE,O)",
        "IsTangentOfCircle(DB,O)",
        "IsTangentOfCircle(DE,O)",
        "IsTangentOfCircle(PA,O)",
        "IsTangentOfCircle(PB,O)"
    ],
    "image_cdl": [],
    "goal_cdl": "Value(Add(LengthOfLine(PC),LengthOfLine(CD),LengthOfLine(DP)))",
    "problem_answer": "30",
    "theorem_seqs": [
        "tangent_of_circle_property_length_equal(1,CE,CA,O)",
        "tangent_of_circle_property_length_equal(1,DE,DB,O)",
        "tangent_of_circle_property_length_equal(1,PA,PB,O)",
        "line_addition(1,BD,DP)",
        "line_addition(1,AC,CP)",
        "line_addition(1,CE,ED)"
    ],
    "theorem_seqs_dag": {
        "START": [
            "tangent_of_circle_property_length_equal(1,CE,CA,O)",
            "tangent_of_circle_property_length_equal(1,DE,DB,O)",
            "tangent_of_circle_property_length_equal(1,PA,PB,O)",
            "line_addition(1,BD,DP)",
            "line_addition(1,AC,CP)",
            "line_addition(1,CE,ED)"
        ]
    }
}