{
    "problem_id": 4836,
    "source": "GeoQA-4294",
    "problem_level": 2,
    "problem_img": "4836.png",
    "construction_cdl": [
        "Shape(TP,PB,OTB)",
        "Shape(OTB,BO,OA,OAT)",
        "Shape(AO,OB,OBA)",
        "Collinear(PBOA)",
        "Cocircular(O,TBA)"
    ],
    "text_cdl": [
        "Equal(LengthOfLine(PB),2)",
        "Equal(LengthOfLine(PT),6)",
        "IsCentreOfCircle(O,O)",
        "IsTangentOfCircle(PT,O)"
    ],
    "image_cdl": [
        "Equal(LengthOfLine(PB),2)",
        "Equal(LengthOfLine(PT),6)",
        "IsTangentOfCircle(PT,O)"
    ],
    "goal_cdl": "Value(LengthOfLine(AB))",
    "problem_answer": "16",
    "theorem_seqs": [
        "line_addition(1,PB,BA)",
        "circle_property_circular_power_tangent_and_segment_line(1,PT,PBA,O)"
    ],
    "theorem_seqs_dag": {
        "START": [
            "line_addition(1,PB,BA)",
            "circle_property_circular_power_tangent_and_segment_line(1,PT,PBA,O)"
        ]
    }
}