{
    "problem_id": 5057,
    "source": "GeoQA-4814",
    "problem_level": 1,
    "problem_img": "5057.png",
    "construction_cdl": [
        "Shape(AD,DE,EA)",
        "Shape(DB,BC,CE,ED)",
        "Collinear(ADB)",
        "Collinear(AEC)"
    ],
    "text_cdl": [
        "Equal(MeasureOfAngle(ADE),80)",
        "Equal(MeasureOfAngle(EAD),60)",
        "MirrorSimilarBetweenTriangle(ABC,ADE)"
    ],
    "image_cdl": [],
    "goal_cdl": "Value(MeasureOfAngle(BCE))",
    "problem_answer": "80",
    "theorem_seqs": [
        "mirror_similar_triangle_property_angle_equal(1,CAB,DEA)"
    ],
    "theorem_seqs_dag": {
        "START": [
            "mirror_similar_triangle_property_angle_equal(1,CAB,DEA)"
        ]
    }
}