{
    "problem_id": 5112,
    "source": "GeoQA-4961",
    "problem_level": 1,
    "problem_img": "5112.png",
    "construction_cdl": [
        "Shape(AE,ED,DA)",
        "Shape(DE,EC,CD)",
        "Shape(DC,CB,BD)",
        "Collinear(AEC)",
        "Collinear(ADB)"
    ],
    "text_cdl": [
        "Equal(LengthOfLine(AB),8)",
        "Equal(MeasureOfAngle(DAE),30)",
        "IsMidpointOfLine(D,AB)",
        "PerpendicularBetweenLine(AC,BC)",
        "PerpendicularBetweenLine(AE,DE)"
    ],
    "image_cdl": [],
    "goal_cdl": "Value(LengthOfLine(BC))",
    "problem_answer": "4",
    "theorem_seqs": [
        "sine_theorem(1,BAC)"
    ],
    "theorem_seqs_dag": {
        "START": [
            "sine_theorem(1,BAC)"
        ]
    }
}