{
    "problem_id": 5471,
    "source": "GeoQA-5887",
    "problem_level": 2,
    "problem_img": "5471.png",
    "construction_cdl": [
        "Shape(BA,AC,CB)",
        "Shape(AD,DC,CA)"
    ],
    "text_cdl": [
        "Equal(LengthOfLine(CD),36)",
        "Equal(MeasureOfAngle(ACB),30)",
        "MirrorCongruentBetweenTriangle(BAC,DCA)",
        "PerpendicularBetweenLine(BA,CA)"
    ],
    "image_cdl": [],
    "goal_cdl": "Value(LengthOfLine(BA))",
    "problem_answer": "18",
    "theorem_seqs": [
        "sine_theorem(1,BAC)",
        "mirror_congruent_triangle_property_line_equal(1,ACB,ADC)"
    ],
    "theorem_seqs_dag": {
        "START": [
            "sine_theorem(1,BAC)",
            "mirror_congruent_triangle_property_line_equal(1,ACB,ADC)"
        ]
    }
}