{
    "problem_id": 4012,
    "source": "GeoQA-2004",
    "problem_level": 9,
    "problem_img": "4012.png",
    "construction_cdl": [
        "Shape(FA,FE,AEF)",
        "Shape(EA,AF,AFE)",
        "Shape(HD,DG,DGH)",
        "Shape(GD,DH,DHG)",
        "Shape(MB,BN,BNM)",
        "Shape(NB,BM,BMN)",
        "Shape(LC,CI,CIL)",
        "Shape(IC,CL,CLI)",
        "Shape(AFE,FM,BNM,NL,CIL,IH,DGH,GE)",
        "Collinear(AFMB)",
        "Collinear(BNLC)",
        "Collinear(CIHD)",
        "Collinear(DGEA)",
        "Cocircular(A,FE)",
        "Cocircular(B,NM)",
        "Cocircular(D,GH)",
        "Cocircular(C,IL)"
    ],
    "text_cdl": [
        "Equal(RadiusOfCircle(A),1)",
        "Equal(RadiusOfCircle(B),1)",
        "Equal(RadiusOfCircle(C),1)",
        "Equal(RadiusOfCircle(D),1)",
        "IsCentreOfCircle(A,A)",
        "IsCentreOfCircle(B,B)",
        "IsCentreOfCircle(C,C)",
        "IsCentreOfCircle(D,D)"
    ],
    "image_cdl": [],
    "goal_cdl": "Value(Add(AreaOfSector(AFE),AreaOfSector(BNM),AreaOfSector(CIL),AreaOfSector(DGH)))",
    "problem_answer": "pi",
    "theorem_seqs": [
        "quadrilateral_property_angle_sum(1,ABCD)",
        "arc_property_center_angle(1,AFE,A)",
        "arc_property_center_angle(1,BNM,B)",
        "arc_property_center_angle(1,DGH,D)",
        "arc_property_center_angle(1,CIL,C)",
        "sector_area_formula(1,AFE)",
        "sector_area_formula(1,BNM)",
        "sector_area_formula(1,DGH)",
        "sector_area_formula(1,CIL)"
    ],
    "theorem_seqs_dag": {
        "START": [
            "quadrilateral_property_angle_sum(1,ABCD)",
            "arc_property_center_angle(1,AFE,A)",
            "arc_property_center_angle(1,BNM,B)",
            "arc_property_center_angle(1,DGH,D)",
            "arc_property_center_angle(1,CIL,C)",
            "sector_area_formula(1,AFE)",
            "sector_area_formula(1,BNM)",
            "sector_area_formula(1,DGH)",
            "sector_area_formula(1,CIL)"
        ]
    }
}