{
    "problem_id": 4713,
    "source": "GeoQA-4032",
    "problem_level": 4,
    "problem_img": "4713.png",
    "construction_cdl": [
        "Shape(DP,PA,ODA)",
        "Shape(AD,ODA)",
        "Shape(DA,AO,OB,BD)",
        "Shape(DC,OCD)",
        "Shape(CB,OBC)",
        "Shape(BO,OA,OAB)",
        "Shape(BC,CD,DB)",
        "Collinear(PAOB)",
        "Cocircular(O,ABCD)"
    ],
    "text_cdl": [
        "Equal(MeasureOfAngle(BCD),130)",
        "IsCentreOfCircle(O,O)",
        "IsDiameterOfCircle(AB,O)",
        "IsTangentOfCircle(PD,O)"
    ],
    "image_cdl": [],
    "goal_cdl": "Value(MeasureOfAngle(ADP))",
    "problem_answer": "40",
    "theorem_seqs": [
        "angle_addition(1,BDA,ADP)",
        "diameter_of_circle_property_right_angle(1,BDA,O)",
        "arc_property_circumference_angle_external(1,ODB,C)",
        "circle_property_angle_of_osculation(1,ODB,P)"
    ],
    "theorem_seqs_dag": {
        "START": [
            "angle_addition(1,BDA,ADP)",
            "diameter_of_circle_property_right_angle(1,BDA,O)",
            "arc_property_circumference_angle_external(1,ODB,C)",
            "circle_property_angle_of_osculation(1,ODB,P)"
        ]
    }
}