{
    "problem_id": 5916,
    "source": "GeoQA-8063",
    "problem_level": 3,
    "problem_img": "5916.png",
    "construction_cdl": [
        "Shape(CA,AD,DC)",
        "Shape(CD,DB,BC)",
        "Collinear(ADB)"
    ],
    "text_cdl": [
        "Equal(LengthOfLine(CD),8)",
        "Equal(MeasureOfAngle(ABC),60)",
        "Equal(MeasureOfAngle(ADC),90)",
        "Equal(MeasureOfAngle(CAB),60)",
        "Equal(MeasureOfAngle(CDB),90)"
    ],
    "image_cdl": [],
    "goal_cdl": "Value(LengthOfLine(AB))",
    "problem_answer": "16*sqrt(3)/3",
    "theorem_seqs": [
        "triangle_property_angle_sum(1,CAB)",
        "sine_theorem(1,CAD)",
        "sine_theorem(1,ABC)"
    ],
    "theorem_seqs_dag": {
        "START": [
            "triangle_property_angle_sum(1,CAB)",
            "sine_theorem(1,CAD)",
            "sine_theorem(1,ABC)"
        ]
    }
}