{
    "problem_id": 6129,
    "source": "GeoQA-8685",
    "problem_level": 2,
    "problem_img": "6129.png",
    "construction_cdl": [
        "Shape(BA,OAB)",
        "Shape(AB,BC,CO,OA)",
        "Shape(AO,OC,OCA)",
        "Shape(BC,OBC)",
        "Cocircular(O,ABC)"
    ],
    "text_cdl": [
        "Equal(MeasureOfAngle(ABC),40)",
        "IsCentreOfCircle(O,O)"
    ],
    "image_cdl": [],
    "goal_cdl": "Value(MeasureOfAngle(AOC))",
    "problem_answer": "80",
    "theorem_seqs": [
        "arc_property_center_angle(1,OCA,O)",
        "arc_property_circumference_angle_external(1,OCA,B)"
    ],
    "theorem_seqs_dag": {
        "START": [
            "arc_property_center_angle(1,OCA,O)",
            "arc_property_circumference_angle_external(1,OCA,B)"
        ]
    }
}