{
    "problem_id": 6696,
    "source": "GeoQA-9726",
    "problem_level": 3,
    "problem_img": "6696.png",
    "construction_cdl": [
        "Shape(ODA,AO,OM,MD)",
        "Shape(DM,MB,BD)",
        "Shape(DB,OBD)",
        "Shape(MO,OC,CM)",
        "Shape(BM,MC,OCB)",
        "Shape(OA,OAC,CO)",
        "Collinear(AOMB)",
        "Collinear(DMC)",
        "Cocircular(O,ACBD)"
    ],
    "text_cdl": [
        "Equal(MeasureOfAngle(COA),130)",
        "IsCentreOfCircle(O,O)",
        "IsDiameterOfCircle(AB,O)"
    ],
    "image_cdl": [],
    "goal_cdl": "Value(MeasureOfAngle(BDC))",
    "problem_answer": "25",
    "theorem_seqs": [
        "adjacent_complementary_angle(1,MOC,COA)",
        "arc_property_center_angle(1,OCB,O)",
        "arc_property_circumference_angle_external(1,OCB,D)"
    ],
    "theorem_seqs_dag": {
        "START": [
            "adjacent_complementary_angle(1,MOC,COA)",
            "arc_property_center_angle(1,OCB,O)",
            "arc_property_circumference_angle_external(1,OCB,D)"
        ]
    }
}